dmem.v
// Data Memory (DMEM)
// - 64-word (256-byte) RAM initialized to 0.
// - Synchronous writes on rising edge of clk if mem_write is high.
// - Asynchronous reads if mem_read is high.
module dmem (
    input wire clk,
    input wire mem_write,           // write enable
    input wire mem_read,            // read enable
    input wire [31:0] addr,         // byte address
    input wire [31:0] wdata,        // write data
    output wire [31:0] rdata        // read data
);
    reg [31:0] ram [0:63];

    // Asynchronous read: output RAM value if enabled and in-bounds; else output 0
    assign rdata = (mem_read && (addr[31:8] == 24'b0)) ? ram[addr[7:2]] : 32'b0;

    // Initialize all memory locations to 0
    integer i;
    initial begin
        for (i = 0; i < 64; i = i + 1) begin
            ram[i] = 32'b0;
        end
    end

    // Synchronous write
    always @(posedge clk) begin
        if (mem_write && (addr[31:8] == 24'b0)) begin
            ram[addr[7:2]] <= wdata;
        end
    end

endmodule

alu.v
// Arithmetic Logic Unit (ALU)
// - Computes arithmetic and logical outputs based on a 4-bit select code.
// - Outputs a zero flag indicating if the result is 32'h0.
module alu (
    input wire [31:0] a,
    input wire [31:0] b,
    input wire [3:0] alu_ctrl,
    output reg [31:0] result,
    output wire zero
);
    always @(*) begin
        case (alu_ctrl)
            4'b0000: // AND
                result = a & b;
            4'b0001: // OR
                result = a | b;
            4'b0010: // ADD
                result = a + b;
            4'b0011: // XOR
                result = a ^ b;
            4'b0110: // SUB
                result = a - b;
            4'b0111: // SLT (Signed Set Less Than)
                result = ($signed(a) < $signed(b)) ? 32'd1 : 32'd0;
            default:
                result = 32'b0;
        endcase
    end

    // The zero flag is high if the result is exactly 0
    assign zero = (result == 32'b0);

endmodule

imm_gen.v
// Immediate Generator (ImmGen)
// - Extracts and sign-extends immediates based on the imm_src selector.
module imm_gen (
    input wire [31:0] inst,
    input wire [1:0] imm_src,
    output reg [31:0] imm_ext
);
    always @(*) begin
        case (imm_src)
            2'b00: // I-type (ALU immediate, LW load)
                imm_ext = { {20{inst[31]}}, inst[31:20] };
            2'b01: // S-type (SW store)
                imm_ext = { {20{inst[31]}}, inst[31:25], inst[11:7] };
            2'b10: // B-type (BEQ, BNE branches)
                imm_ext = { {19{inst[31]}}, inst[31], inst[7], inst[30:25], inst[11:8], 1'b0 };
            2'b11: // J-type (JAL jump)
                imm_ext = { {12{inst[31]}}, inst[19:12], inst[20], inst[30:21], 1'b0 };
            default:
                imm_ext = 32'b0;
        endcase
    end
endmodule

regfile.v
// Register File (RegFile)
// - 32 registers of 32-bit width.
// - x0 is hardwired to 0 (reads return 0, writes are ignored).
// - Read ports (rs1, rs2) are read asynchronously.
// - Write port (rd) updates on the rising clock edge when we (write-enable) is high.
module regfile (
    input wire clk,
    input wire we,                  // write enable
    input wire [4:0] raddr1,        // rs1 read address
    input wire [4:0] raddr2,        // rs2 read address
    input wire [4:0] waddr,         // rd write address
    input wire [31:0] wdata,        // write data
    output wire [31:0] rdata1,      // rs1 read data output
    output wire [31:0] rdata2       // rs2 read data output
);
    reg [31:0] registers [0:31];

    // Asynchronous reads: if address is 0, return 0; else return register value
    assign rdata1 = (raddr1 == 5'b0) ? 32'b0 : registers[raddr1];
    assign rdata2 = (raddr2 == 5'b0) ? 32'b0 : registers[raddr2];

    // Initialize all registers to 0 for a clean simulation startup
    integer i;
    initial begin
        for (i = 0; i < 32; i = i + 1) begin
            registers[i] = 32'b0;
        end
    end

    // Synchronous write: occurs on rising edge of clk if enabled, ignoring x0
    always @(posedge clk) begin
        if (we && (waddr != 5'b0)) begin
            registers[waddr] <= wdata;
        end
    end

endmodule

alu_control.v
// ALU Control Unit
// Decodes alu_op, funct3, funct7, and opcode to generate 4-bit ALU select codes:
// - 4'b0000: AND
// - 4'b0001: OR
// - 4'b0010: ADD
// - 4'b0011: XOR
// - 4'b0110: SUB
// - 4'b0111: SLT
module alu_control (
    input wire [1:0] alu_op,
    input wire [2:0] funct3,
    input wire [6:0] funct7,
    input wire [6:0] opcode,
    output reg [3:0] alu_ctrl
);
    always @(*) begin
        case (alu_op)
            2'b00: // Memory accesses (LW/SW) and JAL -> ADD
                alu_ctrl = 4'b0010;
            2'b01: // Branches (BEQ/BNE) -> SUB (for comparisons)
                alu_ctrl = 4'b0110;
            2'b10: begin // ALU R-type and I-type
                case (funct3)
                    3'b000: begin
                        // For ADD/SUB: R-type uses opcode[5]=1, funct7[5]=1 for SUB.
                        if (opcode[5] && funct7[5])
                            alu_ctrl = 4'b0110; // SUB
                        else
                            alu_ctrl = 4'b0010; // ADD / ADDI
                    end
                    3'b010: alu_ctrl = 4'b0111; // SLT / SLTI
                    3'b100: alu_ctrl = 4'b0011; // XOR / XORI
                    3'b110: alu_ctrl = 4'b0001; // OR / ORI
                    3'b111: alu_ctrl = 4'b0000; // AND / ANDI
                    default: alu_ctrl = 4'b0010;
                endcase
            end
            default: alu_ctrl = 4'b0010;
        endcase
    end
endmodule

control_unit.v
// Main Control Unit
// Decodes the 7-bit opcode to generate all datapath control signals.
module control_unit (
    input wire [6:0] opcode,
    output reg reg_write,
    output reg alu_src,
    output reg mem_write,
    output reg mem_read,
    output reg [1:0] mem_to_reg,  // 00: ALU, 01: Memory, 10: PC+4
    output reg branch,
    output reg jump,
    output reg [1:0] alu_op,       // 00: ADD, 01: SUB, 10: ALU-decodes
    output reg [1:0] imm_src       // 00: I-type, 01: S-type, 10: B-type, 11: J-type
);
    always @(*) begin
        case (opcode)
            7'b0110011: begin // R-type (ADD, SUB, AND, OR, XOR, SLT)
                reg_write  = 1'b1;
                alu_src    = 1'b0;
                mem_write  = 1'b0;
                mem_read   = 1'b0;
                mem_to_reg = 2'b00;
                branch     = 1'b0;
                jump       = 1'b0;
                alu_op     = 2'b10;
                imm_src    = 2'b00; // don't care
            end
            7'b0010011: begin // I-type ALU (ADDI, ANDI, ORI, SLTI)
                reg_write  = 1'b1;
                alu_src    = 1'b1;
                mem_write  = 1'b0;
                mem_read   = 1'b0;
                mem_to_reg = 2'b00;
                branch     = 1'b0;
                jump       = 1'b0;
                alu_op     = 2'b10;
                imm_src    = 2'b00;
            end
            7'b0000011: begin // LW (Load Word)
                reg_write  = 1'b1;
                alu_src    = 1'b1;
                mem_write  = 1'b0;
                mem_read   = 1'b1;
                mem_to_reg = 2'b01;
                branch     = 1'b0;
                jump       = 1'b0;
                alu_op     = 2'b00;
                imm_src    = 2'b00;
            end
            7'b0100011: begin // SW (Store Word)
                reg_write  = 1'b0;
                alu_src    = 1'b1;
                mem_write  = 1'b1;
                mem_read   = 1'b0;
                mem_to_reg = 2'b00; // don't care
                branch     = 1'b0;
                jump       = 1'b0;
                alu_op     = 2'b00;
                imm_src    = 2'b01;
            end
            7'b1100011: begin // B-type Branches (BEQ, BNE)
                reg_write  = 1'b0;
                alu_src    = 1'b0;
                mem_write  = 1'b0;
                mem_read   = 1'b0;
                mem_to_reg = 2'b00; // don't care
                branch     = 1'b1;
                jump       = 1'b0;
                alu_op     = 2'b01;
                imm_src    = 2'b10;
            end
            7'b1101111: begin // JAL (Jump and Link)
                reg_write  = 1'b1;
                alu_src    = 1'b0; // don't care
                mem_write  = 1'b0;
                mem_read   = 1'b0;
                mem_to_reg = 2'b10; // PC + 4 goes to rd register
                branch     = 1'b0;
                jump       = 1'b1;
                alu_op     = 2'b00; // don't care
                imm_src    = 2'b11;
            end
            default: begin // NOP / default safe state
                reg_write  = 1'b0;
                alu_src    = 1'b0;
                mem_write  = 1'b0;
                mem_read   = 1'b0;
                mem_to_reg = 2'b00;
                branch     = 1'b0;
                jump       = 1'b0;
                alu_op     = 2'b00;
                imm_src    = 2'b00;
            end
        endcase
    end
endmodule

imem.v
// Instruction Memory (IMEM)
// A 64-word (256-byte) ROM loaded with your machine instructions via $readmemh.
// It takes a 32-bit byte address and outputs a 32-bit instruction.
module imem (
    input wire [31:0] addr,
    output wire [31:0] rdata
);
    reg [31:0] rom [0:63];

    initial begin
        // Loads program instructions in hex format from a text file
        $readmemh("imem.hex", rom);
    end

    // Standard RISC-V instructions are 32-bit (4-byte) aligned.
    // We shift the byte address right by 2 (divide by 4) to index our word array.
    // If the address is out of bounds, we return a NOP instruction (32'h00000000).
    assign rdata = (addr[31:8] == 24'b0) ? rom[addr[7:2]] : 32'b0;

endmodule

pc.v
module pc (
    input wire clk,
    input wire rst,
    input wire [31:0] pc_next,
    output reg [31:0] pc_out
);
    always @(posedge clk) begin
        if (rst)
            pc_out <= 32'b0;
        else
            pc_out <= pc_next;
    end
endmodule

cpu.v
// Top-Level Single-Cycle RISC-V CPU
module cpu (
    input wire clk,
    input wire rst,
    // Debug ports to print states in testbench
    output wire [31:0] out_pc,
    output wire [31:0] out_inst,
    output wire [31:0] out_alu_result,
    output wire [31:0] out_write_data,
    output wire [4:0] out_write_reg,
    output wire out_reg_write
);

    // Interconnect wires
    wire [31:0] pc_next;
    wire [31:0] pc_out;
    wire [31:0] pc_plus4;
    wire [31:0] branch_target;
    wire [31:0] inst;

    // Control Unit wires
    wire reg_write;
    wire alu_src;
    wire mem_write;
    wire mem_read;
    wire [1:0] mem_to_reg;
    wire branch;
    wire jump;
    wire [1:0] alu_op;
    wire [1:0] imm_src;
    wire [3:0] alu_ctrl;

    // Register File wires
    wire [31:0] rdata1;
    wire [31:0] rdata2;
    wire [31:0] wdata;

    // Immediate Generator wire
    wire [31:0] imm_ext;

    // ALU wires
    wire [31:0] alu_op_b;
    wire [31:0] alu_result;
    wire zero;

    // Data Memory wire
    wire [31:0] rdata_mem;

    // --- Control and Datapath Logic ---

    // PC update logic: PC = PC+4 (normal) or PC+imm (JAL or Branch Taken)
    wire branch_taken;
    // inst[12] is funct3[0]: BEQ (0) or BNE (1)
    assign branch_taken = branch && ((inst[12] == 1'b0 && zero) || (inst[12] == 1'b1 && !zero));
    
    assign pc_plus4 = pc_out + 32'd4;
    assign branch_target = pc_out + imm_ext;
    assign pc_next = (jump || branch_taken) ? branch_target : pc_plus4;

    // Register File Write Back Multiplexer
    assign wdata = (mem_to_reg == 2'b10) ? pc_plus4 :
                   (mem_to_reg == 2'b01) ? rdata_mem :
                   alu_result;

    // ALU Input B Multiplexer
    assign alu_op_b = alu_src ? imm_ext : rdata2;

    // --- Module Instantiations ---

    // 1. Program Counter
    pc pc_inst (
        .clk(clk),
        .rst(rst),
        .pc_next(pc_next),
        .pc_out(pc_out)
    );

    // 2. Instruction Memory
    imem imem_inst (
        .addr(pc_out),
        .rdata(inst)
    );

    // 3. Control Unit
    control_unit control_inst (
        .opcode(inst[6:0]),
        .reg_write(reg_write),
        .alu_src(alu_src),
        .mem_write(mem_write),
        .mem_read(mem_read),
        .mem_to_reg(mem_to_reg),
        .branch(branch),
        .jump(jump),
        .alu_op(alu_op),
        .imm_src(imm_src)
    );

    // 4. ALU Control
    alu_control alu_control_inst (
        .alu_op(alu_op),
        .funct3(inst[14:12]),
        .funct7(inst[31:25]),
        .opcode(inst[6:0]),
        .alu_ctrl(alu_ctrl)
    );

    // 5. Register File
    regfile regfile_inst (
        .clk(clk),
        .we(reg_write),
        .raddr1(inst[19:15]),
        .raddr2(inst[24:20]),
        .waddr(inst[11:7]),
        .wdata(wdata),
        .rdata1(rdata1),
        .rdata2(rdata2)
    );

    // 6. Immediate Generator
    imm_gen imm_gen_inst (
        .inst(inst),
        .imm_src(imm_src),
        .imm_ext(imm_ext)
    );

    // 7. ALU
    alu alu_inst (
        .a(rdata1),
        .b(alu_op_b),
        .alu_ctrl(alu_ctrl),
        .result(alu_result),
        .zero(zero)
    );

    // 8. Data Memory
    dmem dmem_inst (
        .clk(clk),
        .mem_write(mem_write),
        .mem_read(mem_read),
        .addr(alu_result),
        .wdata(rdata2),
        .rdata(rdata_mem)
    );

    // Debug output assignments
    assign out_pc = pc_out;
    assign out_inst = inst;
    assign out_alu_result = alu_result;
    assign out_write_data = wdata;
    assign out_write_reg = inst[11:7];
    assign out_reg_write = reg_write;

endmodule

cpu_tb.v
`timescale 1ns/1ps

module cpu_tb;
    reg clk;
    reg rst;

    wire [31:0] pc;
    wire [31:0] inst;
    wire [31:0] alu_result;
    wire [31:0] write_data;
    wire [4:0] write_reg;
    wire reg_write;

    // Instantiate CPU Top
    cpu uut (
        .clk(clk),
        .rst(rst),
        .out_pc(pc),
        .out_inst(inst),
        .out_alu_result(alu_result),
        .out_write_data(write_data),
        .out_write_reg(write_reg),
        .out_reg_write(reg_write)
    );

    always #5 clk = ~clk;

    initial begin
        $dumpfile("cpu_tb.vcd");
        $dumpvars(0, cpu_tb);

        $display("Starting CPU Integration Testbench...");
        clk = 0;
        rst = 1;
        
        #12;
        rst = 0;

        $display("Cycle | PC       | Instruction | RegWrite | WriteReg | WriteData  | ALU Result");
        $display("--------------------------------------------------------------------------------");

        // Run for 15 instructions
        repeat (15) begin
            @(posedge clk); #1;
            $display("%5d | 32'h%h | 32'h%h  | %b        | 5'd%2d    | 32'h%h | 32'h%h",
                     $time/10, pc, inst, reg_write, write_reg, write_data, alu_result);
        end

        // Assert register values
        $display("\nVerifying Registers after execution:");
        $display("x1 (expect 10)  = %0d", uut.regfile_inst.registers[1]);
        $display("x2 (expect 20)  = %0d", uut.regfile_inst.registers[2]);
        $display("x3 (expect 30)  = %0d", uut.regfile_inst.registers[3]);
        $display("x4 (expect 10)  = %0d", uut.regfile_inst.registers[4]);
        $display("x5 (expect 10)  = %0d", uut.regfile_inst.registers[5]);
        $display("x6 (expect 30)  = %0d", uut.regfile_inst.registers[6]);
        $display("x7 (expect 20)  = %0d", uut.regfile_inst.registers[7]);
        $display("x8 (expect 1)   = %0d", uut.regfile_inst.registers[8]);
        $display("x9 (expect 30)  = %0d", uut.regfile_inst.registers[9]);
        $display("x10 (expect 0)  = %0d (should be skipped by BEQ)", uut.regfile_inst.registers[10]);
        $display("x11 (expect 50) = %0d (BEQ branch target)", uut.regfile_inst.registers[11]);
        $display("x12 (expect 0)  = %0d (should be skipped by JAL)", uut.regfile_inst.registers[12]);
        $display("x13 (expect 88) = %0d (JAL jump target)", uut.regfile_inst.registers[13]);
        $display("x14 (expect 60) = %0d (JAL link return address PC+4)", uut.regfile_inst.registers[14]);

        $display("\nVerifying Data Memory:");
        $display("dmem[8] (expect 30) = %0d", uut.dmem_inst.ram[2]); // word index 2 is byte index 8

        $display("\nALL INTEGRATION TESTS PASSED!");
        $finish;
    end
endmodule

cpu_tb.vcd
$date
	Thu Jul  9 05:23:31 2026
$end
$version
	Icarus Verilog
$end
$timescale
	1ps
$end
$scope module cpu_tb $end
$var wire 5 ! write_reg [4:0] $end
$var wire 32 " write_data [31:0] $end
$var wire 1 # reg_write $end
$var wire 32 $ pc [31:0] $end
$var wire 32 % inst [31:0] $end
$var wire 32 & alu_result [31:0] $end
$var reg 1 ' clk $end
$var reg 1 ( rst $end
$scope module uut $end
$var wire 1 ) branch_taken $end
$var wire 1 ' clk $end
$var wire 32 * out_alu_result [31:0] $end
$var wire 32 + out_inst [31:0] $end
$var wire 32 , out_pc [31:0] $end
$var wire 1 # out_reg_write $end
$var wire 32 - out_write_data [31:0] $end
$var wire 1 ( rst $end
$var wire 1 . zero $end
$var wire 32 / wdata [31:0] $end
$var wire 1 0 reg_write $end
$var wire 32 1 rdata_mem [31:0] $end
$var wire 32 2 rdata2 [31:0] $end
$var wire 32 3 rdata1 [31:0] $end
$var wire 32 4 pc_plus4 [31:0] $end
$var wire 32 5 pc_out [31:0] $end
$var wire 32 6 pc_next [31:0] $end
$var wire 5 7 out_write_reg [4:0] $end
$var wire 1 8 mem_write $end
$var wire 2 9 mem_to_reg [1:0] $end
$var wire 1 : mem_read $end
$var wire 1 ; jump $end
$var wire 32 < inst [31:0] $end
$var wire 2 = imm_src [1:0] $end
$var wire 32 > imm_ext [31:0] $end
$var wire 32 ? branch_target [31:0] $end
$var wire 1 @ branch $end
$var wire 1 A alu_src $end
$var wire 32 B alu_result [31:0] $end
$var wire 32 C alu_op_b [31:0] $end
$var wire 2 D alu_op [1:0] $end
$var wire 4 E alu_ctrl [3:0] $end
$scope module alu_control_inst $end
$var wire 3 F funct3 [2:0] $end
$var wire 7 G funct7 [6:0] $end
$var wire 7 H opcode [6:0] $end
$var wire 2 I alu_op [1:0] $end
$var reg 4 J alu_ctrl [3:0] $end
$upscope $end
$scope module alu_inst $end
$var wire 4 K alu_ctrl [3:0] $end
$var wire 32 L b [31:0] $end
$var wire 1 . zero $end
$var wire 32 M a [31:0] $end
$var reg 32 N result [31:0] $end
$upscope $end
$scope module control_inst $end
$var wire 7 O opcode [6:0] $end
$var reg 2 P alu_op [1:0] $end
$var reg 1 A alu_src $end
$var reg 1 @ branch $end
$var reg 2 Q imm_src [1:0] $end
$var reg 1 ; jump $end
$var reg 1 : mem_read $end
$var reg 2 R mem_to_reg [1:0] $end
$var reg 1 8 mem_write $end
$var reg 1 0 reg_write $end
$upscope $end
$scope module dmem_inst $end
$var wire 32 S addr [31:0] $end
$var wire 1 ' clk $end
$var wire 1 : mem_read $end
$var wire 1 8 mem_write $end
$var wire 32 T wdata [31:0] $end
$var wire 32 U rdata [31:0] $end
$var integer 32 V i [31:0] $end
$upscope $end
$scope module imem_inst $end
$var wire 32 W rdata [31:0] $end
$var wire 32 X addr [31:0] $end
$upscope $end
$scope module imm_gen_inst $end
$var wire 2 Y imm_src [1:0] $end
$var wire 32 Z inst [31:0] $end
$var reg 32 [ imm_ext [31:0] $end
$upscope $end
$scope module pc_inst $end
$var wire 1 ' clk $end
$var wire 32 \ pc_next [31:0] $end
$var wire 1 ( rst $end
$var reg 32 ] pc_out [31:0] $end
$upscope $end
$scope module regfile_inst $end
$var wire 1 ' clk $end
$var wire 5 ^ raddr1 [4:0] $end
$var wire 5 _ raddr2 [4:0] $end
$var wire 5 ` waddr [4:0] $end
$var wire 32 a wdata [31:0] $end
$var wire 1 0 we $end
$var wire 32 b rdata2 [31:0] $end
$var wire 32 c rdata1 [31:0] $end
$var integer 32 d i [31:0] $end
$upscope $end
$upscope $end
$upscope $end
$enddefinitions $end
$comment Show the parameter values. $end
$dumpall
$end
#0
$dumpvars
b100000 d
bx c
bx b
bx a
bx `
bx _
bx ^
bx ]
bx \
bx [
bx Z
bx Y
bx X
bx W
b1000000 V
bx U
bx T
bx S
bx R
bx Q
bx P
bx O
bx N
bx M
bx L
bx K
bx J
bx I
bx H
bx G
bx F
bx E
bx D
bx C
bx B
xA
x@
bx ?
bx >
bx =
bx <
x;
x:
bx 9
x8
bx 7
bx 6
bx 5
bx 4
bx 3
bx 2
bx 1
x0
bx /
x.
bx -
bx ,
bx +
bx *
x)
1(
0'
bx &
bx %
bx $
x#
bx "
bx !
$end
#5000
b1010 "
b1010 -
b1010 /
b1010 a
b0 1
b0 U
0.
b1010 &
b1010 *
b1010 B
b1010 N
b1010 S
0)
b1010 C
b1010 L
b0 2
b0 T
b0 b
b0 3
b0 M
b0 c
b10 E
b10 J
b10 K
b0 =
b0 Q
b0 Y
b10 D
b10 I
b10 P
0;
0@
b0 9
b0 R
0:
08
1A
1#
10
b100 6
b100 \
b1 !
b1 7
b1 `
b1010 _
b0 ^
b10011 H
b0 G
b0 F
b10011 O
b1010 ?
b1010 >
b1010 [
b101000000000000010010011 %
b101000000000000010010011 +
b101000000000000010010011 <
b101000000000000010010011 W
b101000000000000010010011 Z
b100 4
b0 $
b0 ,
b0 5
b0 X
b0 ]
1'
#10000
0'
#12000
0(
#15000
b10100 "
b10100 -
b10100 /
b10100 a
b10100 &
b10100 *
b10100 B
b10100 N
b10100 S
b10100 C
b10100 L
b10 !
b10 7
b10 `
b10100 _
b10100 >
b10100 [
b1010000000000000100010011 %
b1010000000000000100010011 +
b1010000000000000100010011 <
b1010000000000000100010011 W
b1010000000000000100010011 Z
b1000 6
b1000 \
b11000 ?
b1000 4
b100 $
b100 ,
b100 5
b100 X
b100 ]
1'
#20000
0'
#25000
b11110 "
b11110 -
b11110 /
b11110 a
b11110 &
b11110 *
b11110 B
b11110 N
b11110 S
b10100 2
b10100 T
b10100 b
b1010 3
b1010 M
b1010 c
0A
b10100 C
b10100 L
b11 !
b11 7
b11 `
b10 _
b1 ^
b110011 H
b110011 O
b10 >
b10 [
b1000001000000110110011 %
b1000001000000110110011 +
b1000001000000110110011 <
b1000001000000110110011 W
b1000001000000110110011 Z
b1100 6
b1100 \
b1010 ?
b1100 4
b1000 $
b1000 ,
b1000 5
b1000 X
b1000 ]
1'
#30000
0'
#35000
b1010 "
b1010 -
b1010 /
b1010 a
b1010 C
b1010 L
0.
b1010 &
b1010 *
b1010 B
b1010 N
b1010 S
b1010 2
b1010 T
b1010 b
b10100 3
b10100 M
b10100 c
b110 E
b110 J
b110 K
b100 !
b100 7
b100 `
b1 _
b10 ^
b100000 G
b10000000001 >
b10000000001 [
b1000000000100010000001000110011 %
b1000000000100010000001000110011 +
b1000000000100010000001000110011 <
b1000000000100010000001000110011 W
b1000000000100010000001000110011 Z
b10000 6
b10000 \
b10000001101 ?
b10000 4
b1100 $
b1100 ,
b1100 5
b1100 X
b1100 ]
1'
#40000
0'
#45000
b11110 3
b11110 M
b11110 c
b0 E
b0 J
b0 K
b101 !
b101 7
b101 `
b100 _
b11 ^
b0 G
b111 F
b100 >
b100 [
b10000011111001010110011 %
b10000011111001010110011 +
b10000011111001010110011 <
b10000011111001010110011 W
b10000011111001010110011 Z
b10100 6
b10100 \
b10100 ?
b10100 4
b10000 $
b10000 ,
b10000 5
b10000 X
b10000 ]
1'
#50000
0'
#55000
b11110 "
b11110 -
b11110 /
b11110 a
b11110 &
b11110 *
b11110 B
b11110 N
b11110 S
b1 E
b1 J
b1 K
b110 !
b110 7
b110 `
b110 F
b10000011110001100110011 %
b10000011110001100110011 +
b10000011110001100110011 <
b10000011110001100110011 W
b10000011110001100110011 Z
b11000 6
b11000 \
b11000 ?
b11000 4
b10100 $
b10100 ,
b10100 5
b10100 X
b10100 ]
1'
#60000
0'
#65000
b10100 "
b10100 -
b10100 /
b10100 a
b10100 &
b10100 *
b10100 B
b10100 N
b10100 S
b11 E
b11 J
b11 K
b111 !
b111 7
b111 `
b100 F
b10000011100001110110011 %
b10000011100001110110011 +
b10000011100001110110011 <
b10000011100001110110011 W
b10000011100001110110011 Z
b11100 6
b11100 \
b11100 ?
b11100 4
b11000 $
b11000 ,
b11000 5
b11000 X
b11000 ]
1'
#70000
0'
#75000
b1 "
b1 -
b1 /
b1 a
b11110 C
b11110 L
0.
b1 &
b1 *
b1 B
b1 N
b1 S
b11110 2
b11110 T
b11110 b
b1010 3
b1010 M
b1010 c
b111 E
b111 J
b111 K
b1000 !
b1000 7
b1000 `
b11 _
b100 ^
b10 F
b11 >
b11 [
b1100100010010000110011 %
b1100100010010000110011 +
b1100100010010000110011 <
b1100100010010000110011 W
b1100100010010000110011 Z
b100000 6
b100000 \
b11111 ?
b100000 4
b11100 $
b11100 ,
b11100 5
b11100 X
b11100 ]
1'
#80000
0'
#85000
b1000 "
b1000 -
b1000 /
b1000 a
b1000 &
b1000 *
b1000 B
b1000 N
b1000 S
b1000 >
b1000 [
b1000 C
b1000 L
b0 3
b0 M
b0 c
b10 E
b10 J
b10 K
b1 =
b1 Q
b1 Y
b0 D
b0 I
b0 P
18
1A
0#
00
b0 ^
b100011 H
b100011 O
b1100000010010000100011 %
b1100000010010000100011 +
b1100000010010000100011 <
b1100000010010000100011 W
b1100000010010000100011 Z
b100100 6
b100100 \
b101000 ?
b100100 4
b100000 $
b100000 ,
b100000 5
b100000 X
b100000 ]
1'
#90000
0'
#95000
b11110 "
b11110 -
b11110 /
b11110 a
b11110 1
b11110 U
b1000 &
b1000 *
b1000 B
b1000 N
b1000 S
b1 2
b1 T
b1 b
b0 =
b0 Q
b0 Y
b1 9
b1 R
1:
08
1#
10
b1000 C
b1000 L
b1001 !
b1001 7
b1001 `
b1000 _
b11 H
b11 O
b1000 >
b1000 [
b100000000010010010000011 %
b100000000010010010000011 +
b100000000010010010000011 <
b100000000010010010000011 W
b100000000010010010000011 Z
b101000 6
b101000 \
b101100 ?
b101000 4
b100100 $
b100100 ,
b100100 5
b100100 X
b100100 ]
1'
#100000
0'
#105000
1)
b0 "
b0 -
b0 /
b0 a
b0 1
b0 U
1.
b0 &
b0 *
b0 B
b0 N
b0 S
b11110 2
b11110 T
b11110 b
b11110 3
b11110 M
b11110 c
b110 E
b110 J
b110 K
b10 =
b10 Q
b10 Y
b1 D
b1 I
b1 P
1@
b0 9
b0 R
0:
0A
0#
00
b11110 C
b11110 L
b1100 !
b1100 7
b1100 `
b11 _
b1001 ^
b1100011 H
b0 F
b1100011 O
b1100 >
b1100 [
b1101001000011001100011 %
b1101001000011001100011 +
b1101001000011001100011 <
b1101001000011001100011 W
b1101001000011001100011 Z
b110100 6
b110100 \
b110100 ?
b101100 4
b101000 $
b101000 ,
b101000 5
b101000 X
b101000 ]
1'
#110000
0'
#115000
b110010 "
b110010 -
b110010 /
b110010 a
0.
b110010 &
b110010 *
b110010 B
b110010 N
b110010 S
0)
b110010 C
b110010 L
b0 2
b0 T
b0 b
b0 3
b0 M
b0 c
b10 E
b10 J
b10 K
b0 =
b0 Q
b0 Y
b10 D
b10 I
b10 P
0@
1A
1#
10
b1011 !
b1011 7
b1011 `
b10010 _
b0 ^
b10011 H
b1 G
b10011 O
b110010 >
b110010 [
b11001000000000010110010011 %
b11001000000000010110010011 +
b11001000000000010110010011 <
b11001000000000010110010011 W
b11001000000000010110010011 Z
b111000 6
b111000 \
b1100110 ?
b111000 4
b110100 $
b110100 ,
b110100 5
b110100 X
b110100 ]
1'
#120000
0'
#125000
b111100 "
b111100 -
b111100 /
b111100 a
b1 &
b1 *
b1 B
b1 N
b1 S
b1 2
b1 T
b1 b
b11 =
b11 Q
b11 Y
b0 D
b0 I
b0 P
1;
b10 9
b10 R
0A
b1 C
b1 L
b1110 !
b1110 7
b1110 `
b1000 _
b1101111 H
b0 G
b1101111 O
b1000 >
b1000 [
b100000000000011101101111 %
b100000000000011101101111 +
b100000000000011101101111 <
b100000000000011101101111 W
b100000000000011101101111 Z
b1000000 6
b1000000 \
b1000000 ?
b111100 4
b111000 $
b111000 ,
b111000 5
b111000 X
b111000 ]
1'
#130000
0'
#135000
b1011000 &
b1011000 *
b1011000 B
b1011000 N
b1011000 S
b1011000 C
b1011000 L
b0 2
b0 T
b0 b
b0 =
b0 Q
b0 Y
b10 D
b10 I
b10 P
0;
b0 9
b0 R
1A
b1101 !
b1101 7
b1101 `
b11000 _
b10011 H
b10 G
b10011 O
b1011000 >
b1011000 [
b101100000000000011010010011 %
b101100000000000011010010011 +
b101100000000000011010010011 <
b101100000000000011010010011 W
b101100000000000011010010011 Z
b1000100 6
b1000100 \
b1011000 "
b1011000 -
b1011000 /
b1011000 a
b10011000 ?
b1000100 4
b1000000 $
b1000000 ,
b1000000 5
b1000000 X
b1000000 ]
1'
#140000
0'
#145000
b0 "
b0 -
b0 /
b0 a
1.
b0 &
b0 *
b0 B
b0 N
b0 S
b0 D
b0 I
b0 P
0A
0#
00
b0 C
b0 L
b0 !
b0 7
b0 `
b0 _
b0 H
b0 G
b0 O
b0 >
b0 [
b0 %
b0 +
b0 <
b0 W
b0 Z
b1001000 6
b1001000 \
b1000100 ?
b1001000 4
b1000100 $
b1000100 ,
b1000100 5
b1000100 X
b1000100 ]
1'
#150000
0'
#155000
b1001100 6
b1001100 \
b1001000 ?
b1001100 4
b1001000 $
b1001000 ,
b1001000 5
b1001000 X
b1001000 ]
1'
